char_similar_z/__init__.py
char_similar_z/char_similarity_std.py
char_similar_z/path_config.py
char_similar_z/data/__init__.py
char_similar_z/data/char_component.dict
char_similar_z/data/char_fourangle.dict
char_similar_z/data/char_frequency.dict
char_similar_z/data/char_number.dict
char_similar_z/data/char_order.dict
char_similar_z/data/char_pinyin.dict
char_similar_z/data/char_stroke.dict
char_similar_z/data/char_struct.dict
char_similar_z-0.2.0.dist-info/METADATA
char_similar_z-0.2.0.dist-info/WHEEL
char_similar_z-0.2.0.dist-info/entry_points.txt
char_similar_z-0.2.0.dist-info/RECORD
