Metadata-Version: 2.4
Name: char-similar-z
Version: 0.2.0
Summary: 计算两个字符的相似度
Author-email: zoushucai <zoushucai@users.noreply.github.com>
Requires-Python: >=3.10
